blackfalcon/__init__.py
blackfalcon/common_lib/__init__.py
blackfalcon/common_lib/hello.py
blackfalcon-0.1.dist-info/METADATA
blackfalcon-0.1.dist-info/WHEEL
blackfalcon-0.1.dist-info/top_level.txt
blackfalcon-0.1.dist-info/RECORD
